mercaripy/__init__.py
mercaripy-1.0.1.dist-info/LICENSE
mercaripy-1.0.1.dist-info/METADATA
mercaripy-1.0.1.dist-info/WHEEL
mercaripy-1.0.1.dist-info/top_level.txt
mercaripy-1.0.1.dist-info/RECORD
